torchdistlog/__init__.py
torchdistlog/logging.py
torchdistlog/tqdm.py
torchdistlog-0.0.2.dist-info/LICENSE
torchdistlog-0.0.2.dist-info/METADATA
torchdistlog-0.0.2.dist-info/WHEEL
torchdistlog-0.0.2.dist-info/top_level.txt
torchdistlog-0.0.2.dist-info/RECORD
