Metadata-Version: 2.1
Name: torchdistlog
Version: 0.0.2
Summary: Logging for distributed PyTorch training.
Home-page: https://github.com/zbr17/torchdistlog
Author: Borui Zhang
Author-email: zhang-br21@mails.tsinghua.edu.cn
License: UNKNOWN
Project-URL: Docs, https://github.com/zbr17/torchdistlog
Platform: UNKNOWN
Classifier: Programming Language :: Python :: 3
Classifier: License :: OSI Approved :: MIT License
Classifier: Operating System :: OS Independent
Requires-Python: >=3.6
License-File: LICENSE
Requires-Dist: torch (>=1.7.0)
